MANIFEST.in
README.rst
setup.py
Ruby_buildtest_config.egg-info/PKG-INFO
Ruby_buildtest_config.egg-info/SOURCES.txt
Ruby_buildtest_config.egg-info/dependency_links.txt
Ruby_buildtest_config.egg-info/requires.txt
Ruby_buildtest_config.egg-info/top_level.txt
buildtest/__init__.py
buildtest/ruby/code/addressable/reference.txt
buildtest/ruby/code/addressable/uri.rb
buildtest/ruby/code/bigdecimal/nlsolve.rb
buildtest/ruby/code/bigdecimal/pi.rb
buildtest/ruby/code/bigdecimal/reference.txt