Metadata-Version: 1.1
Name: Ruby-buildtest-config
Version: 0.6.0
Summary: Ruby tests for buildtest-framework
Home-page: https://github.com/HPC-buildtest/Ruby-buildtest-config
Author: Shahzeb Siddiqui
Author-email: shahzebmsiddiqui@gmail.com
License: GPLv2
Platform: Linux
Classifier: Development Status :: 4 - Beta
Classifier: Environment :: Console
Classifier: Intended Audience :: System Administrators
Classifier: License :: OSI Approved :: GNU General Public License v3 (GPLv3)
Classifier: Operating System :: POSIX :: Linux
Classifier: Programming Language :: Python :: 3.6
Classifier: Topic :: Software Development :: Build Tools
Classifier: Topic :: Software Development :: Testing
